{"pagination":{"next_max_tag_id":"1102515812918015020","deprecation_warning":"next_max_id and min_id are deprecated for this endpoint; use min_tag_id and max_tag_id instead","next_max_id":"1102515812918015020","next_min_id":"1102515891609807762","min_tag_id":"1102515891609807762","next_url":"https:\/\/api.instagram.com\/v1\/tags\/follow4follow\/media\/recent?access_token=1735765841.1fb234f.7ed02bf17507490aa8b365762902052c\u0026max_tag_id=1102515812918015020"},"meta":{"code":200},"data":[{"attribution":null,"tags":["ss9","de\u00e7u","m\u00e9rite","ali","secretstory","follow4follow","choqu\u00e9","karisma","wesh","f4f","tv","followback","jeu"],"type":"image","location":null,"comments":{"count":0,"data":[]},"filter":"Normal","created_time":"1445650157","link":"https:\/\/instagram.com\/p\/9M7FyuoCuS\/","likes":{"count":3,"data":[{"username":"digital_hous","profile_picture":"https:\/\/igcdn-photos-d-a.akamaihd.net\/hphotos-ak-xfa1\/t51.2885-19\/s150x150\/10513990_1619547188296043_1468123412_a.jpg","id":"2032945368","full_name":"Digital Hous"},{"username":"just1908noe","profile_picture":"https:\/\/scontent.cdninstagram.com\/hphotos-xfa1\/t51.2885-19\/11252879_1579148805694017_621980318_a.jpg","id":"1953272037","full_name":"No\u00ebmie Fievet"},{"username":"eddie.clement17","profile_picture":"https:\/\/scontent.cdninstagram.com\/hphotos-xaf1\/l\/t51.2885-19\/s150x150\/12093450_508874545960615_1662145024_a.jpg","id":"2045878517","full_name":"edwin"}]},"images":{"low_resolution":{"url":"https:\/\/scontent.cdninstagram.com\/hphotos-xfa1\/t51.2885-15\/s320x320\/e35\/12145292_748722151941232_561124492_n.jpg","width":320,"height":320},"thumbnail":{"url":"https:\/\/scontent.cdninstagram.com\/hphotos-xfa1\/t51.2885-15\/s150x150\/e35\/12145292_748722151941232_561124492_n.jpg","width":150,"height":150},"standard_resolution":{"url":"https:\/\/scontent.cdninstagram.com\/hphotos-xfa1\/t51.2885-15\/e35\/12145292_748722151941232_561124492_n.jpg","width":480,"height":480}},"users_in_photo":[{"position":{"y":0.44707143,"x":0.82952183},"user":{"username":"secretstorytf1","profile_picture":"https:\/\/scontent.cdninstagram.com\/hphotos-xaf1\/t51.2885-19\/11371245_890442547710750_806088619_a.jpg","id":"48345894","full_name":"Secret Story"}},{"position":{"y":0.41794115,"x":0.17671518},"user":{"username":"tof_beaugrand","profile_picture":"https:\/\/scontent.cdninstagram.com\/hphotos-xaf1\/t51.2885-19\/11850277_1632284940377741_1699210614_a.jpg","id":"349135704","full_name":"Christophe Beaugrand"}}],"caption":{"created_time":"1445650157","text":"#secretstory #ss9 #ali #karisma #f4f #de\u00e7u #follow4follow #choqu\u00e9 #followback #tv #jeu #m\u00e9rite #wesh","from":{"username":"cindyofficiel","profile_picture":"https:\/\/scontent.cdninstagram.com\/hphotos-xfa1\/t51.2885-19\/11931197_1666473683600051_1134649770_a.jpg","id":"1431062057","full_name":"Cindy BCRT"},"id":"1102515893597907249"},"user_has_liked":false,"id":"1102515891609807762_1431062057","user":{"username":"cindyofficiel","profile_picture":"https:\/\/scontent.cdninstagram.com\/hphotos-xfa1\/t51.2885-19\/11931197_1666473683600051_1134649770_a.jpg","id":"1431062057","full_name":"Cindy BCRT"}},{"attribution":null,"tags":["followus","ifollowback","followhim","followbackinstantly","followmeback","followgram","follower","followstagram","followforlike","followher","follow4follow","follow","follownow","ifollow","f4f","following","tagblender","followshoutoutlikecomment","followforfollow","follows","followall","followme","followback","followers","followyou","followbackteam","followalways","followbackalways","followmefollowyou","followmeplease"],"type":"image","location":null,"comments":{"count":0,"data":[]},"filter":"Sutro","created_time":"1445650157","link":"https:\/\/instagram.com\/p\/9M7FypHKJn\/","likes":{"count":3,"data":[{"username":"eddie.clement17","profile_picture":"https:\/\/scontent.cdninstagram.com\/hphotos-xaf1\/l\/t51.2885-19\/s150x150\/12093450_508874545960615_1662145024_a.jpg","id":"2045878517","full_name":"edwin"},{"username":"nancy6467474","profile_picture":"https:\/\/scontent.cdninstagram.com\/hphotos-xaf1\/t51.2885-19\/11820529_493737410785711_995951850_a.jpg","id":"2171840238","full_name":"Nancy"},{"username":"arturofreiremacias","profile_picture":"https:\/\/scontent.cdninstagram.com\/hphotos-xfa1\/t51.2885-19\/s150x150\/12093335_772063422903607_638866607_a.jpg","id":"2209291831","full_name":"@arturo_freireM."}]},"images":{"low_resolution":{"url":"https:\/\/scontent.cdninstagram.com\/hphotos-xaf1\/t51.2885-15\/s320x320\/e35\/12081130_1206974132651161_1505854393_n.jpg","width":320,"height":320},"thumbnail":{"url":"https:\/\/scontent.cdninstagram.com\/hphotos-xfa1\/t51.2885-15\/s150x150\/e35\/c80.0.480.480\/12142415_564419093706118_187452360_n.jpg","width":150,"height":150},"standard_resolution":{"url":"https:\/\/scontent.cdninstagram.com\/hphotos-xaf1\/t51.2885-15\/e35\/12081130_1206974132651161_1505854393_n.jpg","width":640,"height":640}},"users_in_photo":[],"caption":{"created_time":"1445650157","text":"#follow #followme #followback #followforfollow #follow4follow #followers @tags4likesandroidapp #followher #follower #followhim #followbackteam #followall #followbackalways #follows #following #followgram #followalways #tagblender #followstagram #followshoutoutlikecomment #follownow #followus #followmefollowyou #followmeplease #followbackinstantly #f4f #followmeback #followyou #followforlike #ifollowback #ifollow","from":{"username":"arturofreiremacias","profile_picture":"https:\/\/scontent.cdninstagram.com\/hphotos-xfa1\/t51.2885-19\/s150x150\/12093335_772063422903607_638866607_a.jpg","id":"2209291831","full_name":"@arturo_freireM."},"id":"1102515899830411619"},"user_has_liked":false,"id":"1102515891517301351_2209291831","user":{"username":"arturofreiremacias","profile_picture":"https:\/\/scontent.cdninstagram.com\/hphotos-xfa1\/t51.2885-19\/s150x150\/12093335_772063422903607_638866607_a.jpg","id":"2209291831","full_name":"@arturo_freireM."}},{"attribution":null,"tags":["bucharest","romania","happy","bucharestmyhome","f4f","likeforfollow","vscobest","tagsta","girlish","fashioninspiration","igers","jj","follow4follow","likelike","instalove","jj_forum","instatags4likes","look","likeback","followforfollow","ig_bucharest","ig_romania","instasize","takemetroughbucharest","igersbucharest","smile","like4like","instamood","l4l"],"type":"image","location":null,"comments":{"count":0,"data":[]},"filter":"Clarendon","created_time":"1445650157","link":"https:\/\/instagram.com\/p\/9M7Fyhplx4\/","likes":{"count":19,"data":[{"username":"mylovemanifested","profile_picture":"https:\/\/scontent.cdninstagram.com\/hphotos-xaf1\/t51.2885-19\/s150x150\/11428323_832205370219920_1390771545_a.jpg","id":"1567345312","full_name":"jdiaz"},{"username":"kinggb.239","profile_picture":"https:\/\/scontent.cdninstagram.com\/hphotos-xaf1\/t51.2885-19\/s150x150\/11821057_879304102159004_590992409_a.jpg","id":"1435443321","full_name":"\ud83d\udcb8\ud83d\udcafGregory B\ud83d\udcaf\ud83d\udcb8"},{"username":"raffciak","profile_picture":"https:\/\/igcdn-photos-f-a.akamaihd.net\/hphotos-ak-xfa1\/t51.2885-19\/s150x150\/11430200_1476190906009821_262911078_a.jpg","id":"1496596082","full_name":"Rafa\u0142 Go\u0142\u0119biewski"},{"username":"asakonina","profile_picture":"https:\/\/scontent.cdninstagram.com\/hphotos-xaf1\/t51.2885-19\/11377939_1612571512331384_68848778_a.jpg","id":"1712786876","full_name":"ASAKO.N.S."}]},"images":{"low_resolution":{"url":"https:\/\/scontent.cdninstagram.com\/hphotos-xaf1\/t51.2885-15\/s320x320\/e35\/12106215_494689424041775_85182648_n.jpg","width":320,"height":320},"thumbnail":{"url":"https:\/\/scontent.cdninstagram.com\/hphotos-xaf1\/t51.2885-15\/s150x150\/e35\/12106215_494689424041775_85182648_n.jpg","width":150,"height":150},"standard_resolution":{"url":"https:\/\/scontent.cdninstagram.com\/hphotos-xaf1\/t51.2885-15\/s640x640\/sh0.08\/e35\/12106215_494689424041775_85182648_n.jpg","width":640,"height":640}},"users_in_photo":[],"caption":{"created_time":"1445650157","text":"#instasize #vscobest #InstaTags4Likes #instamood #instalove #l4l #f4f #jj_forum #likeforfollow #like4like #fashioninspiration #follow4follow #look #bucharest #bucharestmyhome #romania #takemetroughbucharest #igers #igersbucharest #ig_bucharest #ig_romania #smile #girlish #tagsta #jj #instasize #likeback #likelike #followforfollow #happy","from":{"username":"diannanistor","profile_picture":"https:\/\/scontent.cdninstagram.com\/hphotos-xaf1\/t51.2885-19\/11232471_533872830093161_499296286_a.jpg","id":"226682454","full_name":"Diana Nistor-Boutique By Niss"},"id":"1102515893380210556"},"user_has_liked":false,"id":"1102515891392109688_226682454","user":{"username":"diannanistor","profile_picture":"https:\/\/scontent.cdninstagram.com\/hphotos-xaf1\/t51.2885-19\/11232471_533872830093161_499296286_a.jpg","id":"226682454","full_name":"Diana Nistor-Boutique By Niss"}},{"attribution":null,"tags":["follow","follow4follow"],"type":"image","location":null,"comments":{"count":0,"data":[]},"filter":"Inkwell","created_time":"1445650157","link":"https:\/\/instagram.com\/p\/9M7FxHSxvQ\/","likes":{"count":6,"data":[{"username":"yordytks15","profile_picture":"https:\/\/scontent.cdninstagram.com\/hphotos-xaf1\/t51.2885-19\/11245057_665030900289933_1406559970_a.jpg","id":"1586728840","full_name":"King tks"},{"username":"cesar03_x","profile_picture":"https:\/\/scontent.cdninstagram.com\/hphotos-xaf1\/t51.2885-19\/s150x150\/12145377_1644026145850173_2069281261_a.jpg","id":"581366794","full_name":"c\u00e9sar khalifa :3"},{"username":"eddie.clement17","profile_picture":"https:\/\/scontent.cdninstagram.com\/hphotos-xaf1\/l\/t51.2885-19\/s150x150\/12093450_508874545960615_1662145024_a.jpg","id":"2045878517","full_name":"edwin"},{"username":"cristiankaponi21","profile_picture":"https:\/\/scontent.cdninstagram.com\/hphotos-xfa1\/t51.2885-19\/s150x150\/11821100_997803436907466_287295458_a.jpg","id":"1380686863","full_name":"Cristian kaponi"}]},"images":{"low_resolution":{"url":"https:\/\/scontent.cdninstagram.com\/hphotos-xaf1\/t51.2885-15\/s320x320\/e15\/12080649_892365904181046_1308009483_n.jpg","width":320,"height":320},"thumbnail":{"url":"https:\/\/scontent.cdninstagram.com\/hphotos-xaf1\/t51.2885-15\/s150x150\/e15\/12080649_892365904181046_1308009483_n.jpg","width":150,"height":150},"standard_resolution":{"url":"https:\/\/scontent.cdninstagram.com\/hphotos-xaf1\/t51.2885-15\/e15\/12080649_892365904181046_1308009483_n.jpg","width":612,"height":612}},"users_in_photo":[],"caption":{"created_time":"1445650157","text":"#follow #follow4follow \ud83c\udf83\ud83d\udebc\ud83c\udf3d\ud83c\udf3d\ud83c\udf3d","from":{"username":"sandyrd9","profile_picture":"https:\/\/igcdn-photos-h-a.akamaihd.net\/hphotos-ak-xaf1\/t51.2885-19\/s150x150\/12105093_811448225644111_1364472575_a.jpg","id":"2201639805","full_name":"sandy polanco"},"id":"1102515896243132642"},"user_has_liked":false,"id":"1102515889876179920_2201639805","user":{"username":"sandyrd9","profile_picture":"https:\/\/igcdn-photos-h-a.akamaihd.net\/hphotos-ak-xaf1\/t51.2885-19\/s150x150\/12105093_811448225644111_1364472575_a.jpg","id":"2201639805","full_name":"sandy polanco"}},{"attribution":null,"tags":["and","instachile","instahappy","instalike","meet","instalove","likesforlikes","instasweet","instadreams","insta","likes","seguidores","follow4follow","follow","instamood","instasmile","followforfollow","siguemeytesigo","instagood","i","followers","followyou","f4f","likeforlike","like4like","followme","l4l"],"type":"image","location":null,"comments":{"count":0,"data":[]},"filter":"Normal","created_time":"1445650157","link":"https:\/\/instagram.com\/p\/9M7FssoWHR\/","likes":{"count":18,"data":[{"username":"kishan_rajput20","profile_picture":"https:\/\/igcdn-photos-a-a.akamaihd.net\/hphotos-ak-xaf1\/t51.2885-19\/s150x150\/12070825_924940124245480_923066134_a.jpg","id":"1305386024","full_name":"\u0915\u093f\u0936\u0928 \u0938\u093f\u0902\u0939 \u0938\u0942\u0930\u094d\u092f\u0935\u0902\u0936\u0940"},{"username":"raffciak","profile_picture":"https:\/\/igcdn-photos-f-a.akamaihd.net\/hphotos-ak-xfa1\/t51.2885-19\/s150x150\/11430200_1476190906009821_262911078_a.jpg","id":"1496596082","full_name":"Rafa\u0142 Go\u0142\u0119biewski"},{"username":"asakonina","profile_picture":"https:\/\/scontent.cdninstagram.com\/hphotos-xaf1\/t51.2885-19\/11377939_1612571512331384_68848778_a.jpg","id":"1712786876","full_name":"ASAKO.N.S."},{"username":"brayandaniel_o._.o_","profile_picture":"https:\/\/igcdn-photos-g-a.akamaihd.net\/hphotos-ak-xaf1\/t51.2885-19\/s150x150\/11809986_162565460748054_564836718_a.jpg","id":"1601566630","full_name":"Brayan Daniel \ud83c\udf8b\ud83c\udf00\ud83d\udca6\ud83d\udca5\ud83d\udca6\ud83d\udca5\ud83d\udca6"}]},"images":{"low_resolution":{"url":"https:\/\/scontent.cdninstagram.com\/hphotos-xaf1\/t51.2885-15\/s320x320\/e35\/12071242_1512980352353703_2114782699_n.jpg","width":320,"height":320},"thumbnail":{"url":"https:\/\/scontent.cdninstagram.com\/hphotos-xaf1\/t51.2885-15\/s150x150\/e35\/12071242_1512980352353703_2114782699_n.jpg","width":150,"height":150},"standard_resolution":{"url":"https:\/\/scontent.cdninstagram.com\/hphotos-xaf1\/t51.2885-15\/s640x640\/sh0.08\/e35\/12071242_1512980352353703_2114782699_n.jpg","width":640,"height":640}},"users_in_photo":[],"caption":{"created_time":"1445650157","text":"Ella no es bonita, es una palabra muy peque\u00f1a.\nElla es fuerte, y sus ojos demandan atenci\u00f3n.\nMirarla es como despertar.\n\ud83c\udf38Mario Benedetti \ud83c\udf38\n\n#insta #instachile #instahappy #instasweet #instalove #instagood #instadreams #instalike #instamood #instasmile #likes #likesforlikes #likeforlike #l4l #like4like #follow #followers #followforfollow #f4f #follow4follow #followme #and #I #followyou #I #meet #seguidores  #Siguemeytesigo","from":{"username":"x.sweeet.x","profile_picture":"https:\/\/scontent.cdninstagram.com\/hphotos-xaf1\/t51.2885-19\/s150x150\/12120444_457710227764488_1265819636_a.jpg","id":"365182135","full_name":"Ana\u00eds C\u00e1ceres Valverdi \ud83d\udc9a"},"id":"1102516149928681871"},"user_has_liked":false,"id":"1102515885133881809_365182135","user":{"username":"x.sweeet.x","profile_picture":"https:\/\/scontent.cdninstagram.com\/hphotos-xaf1\/t51.2885-19\/s150x150\/12120444_457710227764488_1265819636_a.jpg","id":"365182135","full_name":"Ana\u00eds C\u00e1ceres Valverdi \ud83d\udc9a"}},{"attribution":null,"tags":["love","followhim","instalove","f4f","likeforfollow","following","follower","followforlike","followher","follow4follow","follow","instadaily","instamood","me","followforfollow","follows","teamfollowback","followall","instagood","followback","likefor10likes","likeforlike","pleasefollow","followbackteam","followalways","like4like","followme"],"type":"image","location":null,"comments":{"count":1,"data":[{"created_time":"1445650492","text":"Damn that's nice","from":{"username":"p.clary","profile_picture":"https:\/\/scontent.cdninstagram.com\/hphotos-xap1\/t51.2885-19\/s150x150\/10818045_556028041211913_329743123_a.jpg","id":"2244352909","full_name":""},"id":"1102518700788202529"}]},"filter":"Normal","created_time":"1445650156","link":"https:\/\/instagram.com\/p\/9M7FnpNLwJ\/","likes":{"count":12,"data":[{"username":"1caiom","profile_picture":"https:\/\/scontent.cdninstagram.com\/hphotos-xaf1\/t51.2885-19\/s150x150\/11312508_792894870827718_1908125048_a.jpg","id":"1911258553","full_name":"Caio Marques \ud83d\udd2b"},{"username":"fardin_moridpour","profile_picture":"https:\/\/scontent.cdninstagram.com\/hphotos-xfp1\/t51.2885-19\/10665439_710694592344485_324359679_a.jpg","id":"1532309356","full_name":"fardin"},{"username":"surykateczka","profile_picture":"https:\/\/scontent.cdninstagram.com\/hphotos-xaf1\/t51.2885-19\/s150x150\/11856568_1621848718079472_785284710_a.jpg","id":"1588088390","full_name":"Natalia Bieniuszewicz"},{"username":"shoutout.of.hotties2","profile_picture":"https:\/\/scontent.cdninstagram.com\/hphotos-xfa1\/t51.2885-19\/s150x150\/12142265_700102746786340_1214204128_a.jpg","id":"1712158374","full_name":"C.Girl - Sweet_angel_sherly"}]},"images":{"low_resolution":{"url":"https:\/\/scontent.cdninstagram.com\/hphotos-xaf1\/t51.2885-15\/s320x320\/e35\/12142161_738006692971628_234238638_n.jpg","width":320,"height":320},"thumbnail":{"url":"https:\/\/scontent.cdninstagram.com\/hphotos-xaf1\/t51.2885-15\/s150x150\/e35\/12142161_738006692971628_234238638_n.jpg","width":150,"height":150},"standard_resolution":{"url":"https:\/\/scontent.cdninstagram.com\/hphotos-xaf1\/t51.2885-15\/e35\/12142161_738006692971628_234238638_n.jpg","width":480,"height":480}},"users_in_photo":[],"caption":{"created_time":"1445650156","text":"Follow @sweet_angel_sherly\ud83d\udc98 \ud83d\udc98 \ud83d\udc98 \ud83d\udc98\n.\n.\nFollow\n@shoutout.of.hotties2\n@shoutout.of.hotties2\n@shoutout.of.hotties2\n#love #followback #followhim #f4f\n#following #follower #followher\n#follow4follow #follow #me #followforfollow\n#follows #teamfollowback #followall\n#pleasefollow #followbackteam\n#followalways #followme \n#instadaily  #instalove #instamood\n#instagood #likeforfollow #likefor10likes\n#followforlike #likeforlike #like4like","from":{"username":"shoutout.of.hotties2","profile_picture":"https:\/\/scontent.cdninstagram.com\/hphotos-xfa1\/t51.2885-19\/s150x150\/12142265_700102746786340_1214204128_a.jpg","id":"1712158374","full_name":"C.Girl - Sweet_angel_sherly"},"id":"1102515882014588794"},"user_has_liked":false,"id":"1102515879707720713_1712158374","user":{"username":"shoutout.of.hotties2","profile_picture":"https:\/\/scontent.cdninstagram.com\/hphotos-xfa1\/t51.2885-19\/s150x150\/12142265_700102746786340_1214204128_a.jpg","id":"1712158374","full_name":"C.Girl - Sweet_angel_sherly"}},{"attribution":null,"tags":["swans","becasuewecan","arenumberone","follow4follow","beenplaces","respectlife","followme"],"type":"image","location":null,"comments":{"count":0,"data":[]},"filter":"Gingham","created_time":"1445650156","link":"https:\/\/instagram.com\/p\/9M7FliGjSC\/","likes":{"count":7,"data":[{"username":"my.fitness_girls","profile_picture":"https:\/\/scontent.cdninstagram.com\/hphotos-xta1\/t51.2885-19\/11084816_1565681397037014_1870343199_a.jpg","id":"1785256298","full_name":"Fitness Girls"},{"username":"alshmmari1","profile_picture":"https:\/\/scontent.cdninstagram.com\/hphotos-xaf1\/t51.2885-19\/11378050_120849054919647_461762669_a.jpg","id":"572461989","full_name":"\u0645\u062d\u0645\u062f \u0627\u0644\u0634\u0645\u0631\u064a"},{"username":"kaju_tz_160","profile_picture":"https:\/\/igcdn-photos-c-a.akamaihd.net\/hphotos-ak-xfa1\/t51.2885-19\/s150x150\/12093479_162543614094530_421551067_a.jpg","id":"1963886326","full_name":"Kaju A Othman"},{"username":"moha_hr","profile_picture":"https:\/\/scontent.cdninstagram.com\/hphotos-xfp1\/t51.2885-19\/1388821_1388230131467467_1384646500_a.jpg","id":"1281314583","full_name":"M7mad Alharbi"}]},"images":{"low_resolution":{"url":"https:\/\/scontent.cdninstagram.com\/hphotos-xfa1\/t51.2885-15\/s320x320\/e35\/12142616_773471112775262_1935244870_n.jpg","width":320,"height":320},"thumbnail":{"url":"https:\/\/scontent.cdninstagram.com\/hphotos-xfa1\/t51.2885-15\/s150x150\/e35\/12142616_773471112775262_1935244870_n.jpg","width":150,"height":150},"standard_resolution":{"url":"https:\/\/scontent.cdninstagram.com\/hphotos-xfa1\/t51.2885-15\/e35\/12142616_773471112775262_1935244870_n.jpg","width":640,"height":640}},"users_in_photo":[],"caption":{"created_time":"1445650156","text":"#swans #arenumberone #beenplaces #becasuewecan #follow4follow #followme #respectlife","from":{"username":"dreamb0ards","profile_picture":"https:\/\/igcdn-photos-f-a.akamaihd.net\/hphotos-ak-xaf1\/t51.2885-19\/s150x150\/12106255_743126622490277_1036172784_a.jpg","id":"2247176676","full_name":"Dream Board"},"id":"1102515880024749682"},"user_has_liked":false,"id":"1102515877441057922_2247176676","user":{"username":"dreamb0ards","profile_picture":"https:\/\/igcdn-photos-f-a.akamaihd.net\/hphotos-ak-xaf1\/t51.2885-19\/s150x150\/12106255_743126622490277_1036172784_a.jpg","id":"2247176676","full_name":"Dream Board"}},{"attribution":null,"tags":["love","picoftheday","food","instalike","toptags","instago","igers","follow4follow","follow","girl","instadaily","style","webstagram","look","instafollow","iphoneonly","20likes","all_shots","instagood","amazing","instacool","bestoftheday","smile","like4like","tweegram","followme","photooftheday"],"type":"image","location":null,"comments":{"count":0,"data":[]},"filter":"Normal","created_time":"1445650155","link":"https:\/\/instagram.com\/p\/9M7FijzRub\/","likes":{"count":10,"data":[{"username":"leah_monk","profile_picture":"https:\/\/igcdn-photos-a-a.akamaihd.net\/hphotos-ak-xaf1\/t51.2885-19\/s150x150\/11849946_1632786786991496_348311573_a.jpg","id":"367341136","full_name":"\u0950 Leah Gabrielle Monk"},{"username":"omar773","profile_picture":"https:\/\/scontent.cdninstagram.com\/hphotos-xaf1\/t51.2885-19\/11245912_470206349804424_1137563925_a.jpg","id":"3310618","full_name":"O.O."},{"username":"michaeldescoteaux","profile_picture":"https:\/\/scontent.cdninstagram.com\/hphotos-xfa1\/t51.2885-19\/s150x150\/12106238_956974961049858_1466786019_a.jpg","id":"365247676","full_name":"Micha\u00ebl Desc\u00f4teaux"},{"username":"alexander_dgr8","profile_picture":"https:\/\/scontent.cdninstagram.com\/hphotos-xaf1\/t51.2885-19\/11363659_800428083411123_2118729418_a.jpg","id":"31305829","full_name":"Alex Bostanian"}]},"images":{"low_resolution":{"url":"https:\/\/scontent.cdninstagram.com\/hphotos-xfa1\/t51.2885-15\/e35\/12141824_1635168066746076_1575179375_n.jpg","width":320,"height":320},"thumbnail":{"url":"https:\/\/scontent.cdninstagram.com\/hphotos-xfa1\/t51.2885-15\/s150x150\/e35\/12141824_1635168066746076_1575179375_n.jpg","width":150,"height":150},"standard_resolution":{"url":"https:\/\/scontent.cdninstagram.com\/hphotos-xfa1\/t51.2885-15\/e35\/12141824_1635168066746076_1575179375_n.jpg","width":320,"height":320}},"users_in_photo":[],"caption":{"created_time":"1445650155","text":"\ud83d\udd1d #love #style @top.tags #toptags #tweegram #photooftheday #20likes #amazing #smile #follow4follow #like4like #look #instalike #igers #picoftheday #food #instadaily #instafollow #followme #girl #iphoneonly #instagood #bestoftheday #instacool #instago #all_shots #follow #webstagram","from":{"username":"noahsyummysnacks","profile_picture":"https:\/\/igcdn-photos-b-a.akamaihd.net\/hphotos-ak-xfa1\/t51.2885-19\/s150x150\/12070949_481251582044793_2094201523_a.jpg","id":"2225074933","full_name":"Food 'R' Us"},"id":"1102515880648841975"},"user_has_liked":false,"id":"1102515874248334235_2225074933","user":{"username":"noahsyummysnacks","profile_picture":"https:\/\/igcdn-photos-b-a.akamaihd.net\/hphotos-ak-xfa1\/t51.2885-19\/s150x150\/12070949_481251582044793_2094201523_a.jpg","id":"2225074933","full_name":"Food 'R' Us"}},{"attribution":null,"tags":["tfl","likeforlikes","nature","lfl","instapic","likeforfollow","likesforlikes","recent4recent","likebackteam","followforfollowback","likes","follow4follow","likesforfollow","follow","instadaily","instagramhub","like4like","follow4like","tflers","likes4likes","followforfollow","likeback","instagood","tagsforlikes","likeforlike","f4f","like4follow","igers"],"type":"image","location":null,"comments":{"count":0,"data":[]},"filter":"Normal","created_time":"1445650155","link":"https:\/\/instagram.com\/p\/9M7FeQG_gx\/","likes":{"count":28,"data":[{"username":"dallas1383","profile_picture":"https:\/\/scontent.cdninstagram.com\/hphotos-xfp1\/t51.2885-19\/10643865_1607095836189413_510142951_a.jpg","id":"1695198488","full_name":"Geraldine Burke"},{"username":"_.frxxn","profile_picture":"https:\/\/scontent.cdninstagram.com\/hphotos-xaf1\/t51.2885-19\/s150x150\/12105129_542288282587378_2100103926_a.jpg","id":"1617007737","full_name":"\ud83d\udc3b\ud83d\udc95\ud83d\udc28"},{"username":"juli_villalon","profile_picture":"https:\/\/scontent.cdninstagram.com\/hphotos-xap1\/t51.2885-19\/11189748_835509666536993_556745578_a.jpg","id":"1562851188","full_name":"Juli villalon"},{"username":"dxpe.daddyy","profile_picture":"https:\/\/igcdn-photos-h-a.akamaihd.net\/hphotos-ak-xaf1\/t51.2885-19\/s150x150\/12107491_937340122971167_1506485613_a.jpg","id":"1704844709","full_name":"Call Me Stanley\ud83d\ude08\ud83d\ude02"}]},"images":{"low_resolution":{"url":"https:\/\/scontent.cdninstagram.com\/hphotos-xaf1\/t51.2885-15\/s320x320\/e35\/12120481_1675477252672374_216483240_n.jpg","width":320,"height":320},"thumbnail":{"url":"https:\/\/scontent.cdninstagram.com\/hphotos-xaf1\/t51.2885-15\/s150x150\/e35\/12120481_1675477252672374_216483240_n.jpg","width":150,"height":150},"standard_resolution":{"url":"https:\/\/scontent.cdninstagram.com\/hphotos-xaf1\/t51.2885-15\/s640x640\/sh0.08\/e35\/12120481_1675477252672374_216483240_n.jpg","width":640,"height":640}},"users_in_photo":[],"caption":{"created_time":"1445650155","text":"#like4like #likes #likeforlike #tfl #instagood #likeforlikes #recent4recent #lfl #instapic #like4follow #follow #likesforlikes #likeforfollow #followforfollowback #follow4like #followforfollow #follow4follow #likes4likes  #tagsforlikes #likesforfollow #f4f #likebackteam #igers #tflers #likeback #like4like #likes #likeforlike #tfl #instagood #nature #instadaily #instagramhub","from":{"username":"_venriquezc_","profile_picture":"https:\/\/scontent.cdninstagram.com\/hphotos-xaf1\/t51.2885-19\/s150x150\/11809660_1153843897976343_38888932_a.jpg","id":"295026789","full_name":"Vannia Enr\u00edquez\ud83d\udc51"},"id":"1102515876929468806"},"user_has_liked":false,"id":"1102515869622990897_295026789","user":{"username":"_venriquezc_","profile_picture":"https:\/\/scontent.cdninstagram.com\/hphotos-xaf1\/t51.2885-19\/s150x150\/11809660_1153843897976343_38888932_a.jpg","id":"295026789","full_name":"Vannia Enr\u00edquez\ud83d\udc51"}},{"attribution":null,"tags":["beautiful","babygirl","allday","followback","instagram","selfie","queen","facebook","makeup","follow4follow","beautifulplace","portrait","cool","hashtag","like4like","mood","bestmoments","kiss","dog","tagsforlikes","lipstick","amazing","cateyes","classy","serious","potd","sweetness","followme","chilling","happy"],"type":"image","location":null,"comments":{"count":0,"data":[]},"filter":"Normal","created_time":"1445650154","link":"https:\/\/instagram.com\/p\/9M7FXIEfRQ\/","likes":{"count":8,"data":[{"username":"nawal753","profile_picture":"https:\/\/igcdn-photos-a-a.akamaihd.net\/hphotos-ak-xfa1\/t51.2885-19\/s150x150\/11910506_468873923293280_1908377341_a.jpg","id":"622095211","full_name":"Nawal \ud83c\udf8e"},{"username":"nol_t_n","profile_picture":"https:\/\/scontent.cdninstagram.com\/hphotos-xfa1\/t51.2885-19\/s150x150\/11311559_969716889716479_559925604_a.jpg","id":"1117611563","full_name":"nol_t_n"},{"username":"ellie_mae_h","profile_picture":"https:\/\/scontent.cdninstagram.com\/hphotos-xfa1\/t51.2885-19\/s150x150\/11252618_869615683125312_539795068_a.jpg","id":"22475627","full_name":"Liz Mae H"},{"username":"alecaccavo","profile_picture":"https:\/\/igcdn-photos-f-a.akamaihd.net\/hphotos-ak-xaf1\/t51.2885-19\/11022892_819735128108413_305352899_a.jpg","id":"211688247","full_name":"Alessandra Caccavo"}]},"images":{"low_resolution":{"url":"https:\/\/scontent.cdninstagram.com\/hphotos-xaf1\/t51.2885-15\/s320x320\/e35\/12093393_554390824715743_1681703159_n.jpg","width":320,"height":320},"thumbnail":{"url":"https:\/\/scontent.cdninstagram.com\/hphotos-xaf1\/t51.2885-15\/s150x150\/e35\/12093393_554390824715743_1681703159_n.jpg","width":150,"height":150},"standard_resolution":{"url":"https:\/\/scontent.cdninstagram.com\/hphotos-xaf1\/t51.2885-15\/s640x640\/sh0.08\/e35\/12093393_554390824715743_1681703159_n.jpg","width":640,"height":640}},"users_in_photo":[],"caption":{"created_time":"1445650154","text":"Friday \ud83d\udc6b\ud83c\udf89\ud83c\udf88\ud83d\ude18\ud83d\udcf7 #classy#cool#followback#follow4follow#followme#tagsforlikes#like4like#beautiful#lipstick#potd#portrait#queen#allday#amazing#selfie#serious#sweetness#dog#followme#follow4follow#happy#hashtag#kiss#lipstick#chilling#beautiful#babygirl#bestmoments#beautifulplace#mood#makeup#cateyes#facebook#instagram","from":{"username":"ester_mil","profile_picture":"https:\/\/igcdn-photos-f-a.akamaihd.net\/hphotos-ak-xaf1\/t51.2885-19\/s150x150\/11856582_186901418309429_1845472941_a.jpg","id":"185196148","full_name":"Ester Milella \ud83d\udc8e"},"id":"1102519662439167827"},"user_has_liked":false,"id":"1102515861971924048_185196148","user":{"username":"ester_mil","profile_picture":"https:\/\/igcdn-photos-f-a.akamaihd.net\/hphotos-ak-xaf1\/t51.2885-19\/s150x150\/11856582_186901418309429_1845472941_a.jpg","id":"185196148","full_name":"Ester Milella \ud83d\udc8e"}},{"attribution":null,"tags":["liampayne","rblra","perfectonedirection","onedirection","louistomlinson","harrystyles","zaynbae","follow4follow","niallhoran","like4like","zaynmalik"],"type":"image","location":null,"comments":{"count":0,"data":[]},"filter":"Normal","created_time":"1445650154","link":"https:\/\/instagram.com\/p\/9M7FU8trl5\/","likes":{"count":4,"data":[{"username":"leah_monk","profile_picture":"https:\/\/igcdn-photos-a-a.akamaihd.net\/hphotos-ak-xaf1\/t51.2885-19\/s150x150\/11849946_1632786786991496_348311573_a.jpg","id":"367341136","full_name":"\u0950 Leah Gabrielle Monk"},{"username":"followflock.t9","profile_picture":"https:\/\/scontent.cdninstagram.com\/hphotos-xaf1\/t51.2885-19\/s150x150\/12142195_538895419625319_820084201_a.jpg","id":"2248465146","full_name":"Get Followers Here"},{"username":"sisi.ab","profile_picture":"https:\/\/scontent.cdninstagram.com\/hphotos-xaf1\/t51.2885-19\/12080599_440765599449204_1560252591_a.jpg","id":"2002532123","full_name":"sisi slh"},{"username":"1dfunny.p0sts","profile_picture":"https:\/\/igcdn-photos-f-a.akamaihd.net\/hphotos-ak-xfa1\/t51.2885-19\/12070928_1057788430900869_1388805952_a.jpg","id":"1565096622","full_name":"Funny 1D p0sts"}]},"images":{"low_resolution":{"url":"https:\/\/scontent.cdninstagram.com\/hphotos-xfa1\/t51.2885-15\/s320x320\/e35\/12144095_152216885133102_1015644813_n.jpg","width":320,"height":320},"thumbnail":{"url":"https:\/\/scontent.cdninstagram.com\/hphotos-xfa1\/t51.2885-15\/s150x150\/e35\/c56.0.887.887\/12107618_539138822904308_829815720_n.jpg","width":150,"height":150},"standard_resolution":{"url":"https:\/\/scontent.cdninstagram.com\/hphotos-xfa1\/t51.2885-15\/s640x640\/sh0.08\/e35\/12144095_152216885133102_1015644813_n.jpg","width":640,"height":640}},"users_in_photo":[],"caption":{"created_time":"1445650154","text":"#perfectonedirection\n#louistomlinson \n#harrystyles\n#liampayne #niallhoran\n#zaynmalik #zaynBAE\n#onedirection \n#follow4follow \n#like4like \n#RBLRA","from":{"username":"roseeee30","profile_picture":"https:\/\/scontent.cdninstagram.com\/hphotos-xpf1\/t51.2885-19\/11004977_410020259167580_1960111082_a.jpg","id":"1138368501","full_name":"roseeee30"},"id":"1102515863995988739"},"user_has_liked":false,"id":"1102515859633912185_1138368501","user":{"username":"roseeee30","profile_picture":"https:\/\/scontent.cdninstagram.com\/hphotos-xpf1\/t51.2885-19\/11004977_410020259167580_1960111082_a.jpg","id":"1138368501","full_name":"roseeee30"}},{"attribution":null,"tags":["love","picoftheday","food","instalike","toptags","littlebrother","instago","igers","follow4follow","follow","girl","instadaily","style","webstagram","look","instafollow","iphoneonly","20likes","all_shots","instagood","amazing","instacool","bestoftheday","smile","like4like","tweegram","followme","photooftheday"],"type":"image","location":null,"comments":{"count":0,"data":[]},"filter":"Reyes","created_time":"1445650153","link":"https:\/\/instagram.com\/p\/9M7FQIEGFL\/","likes":{"count":12,"data":[{"username":"leah_monk","profile_picture":"https:\/\/igcdn-photos-a-a.akamaihd.net\/hphotos-ak-xaf1\/t51.2885-19\/s150x150\/11849946_1632786786991496_348311573_a.jpg","id":"367341136","full_name":"\u0950 Leah Gabrielle Monk"},{"username":"michaeldescoteaux","profile_picture":"https:\/\/scontent.cdninstagram.com\/hphotos-xfa1\/t51.2885-19\/s150x150\/12106238_956974961049858_1466786019_a.jpg","id":"365247676","full_name":"Micha\u00ebl Desc\u00f4teaux"},{"username":"robertocarboni","profile_picture":"https:\/\/scontent.cdninstagram.com\/hphotos-xfa1\/t51.2885-19\/11252282_467564580070695_632802016_a.jpg","id":"42446718","full_name":"Roberto Carboni"},{"username":"createitceramics","profile_picture":"https:\/\/igcdn-photos-b-a.akamaihd.net\/hphotos-ak-xaf1\/t51.2885-19\/11931013_1586822688260609_322213227_a.jpg","id":"187708254","full_name":"Create It Ceramics \u0026 Glass"}]},"images":{"low_resolution":{"url":"https:\/\/scontent.cdninstagram.com\/hphotos-xaf1\/t51.2885-15\/s320x320\/e35\/12071244_1608352556093689_1146212431_n.jpg","width":320,"height":320},"thumbnail":{"url":"https:\/\/scontent.cdninstagram.com\/hphotos-xaf1\/t51.2885-15\/s150x150\/e35\/c216.0.648.648\/12135252_436243063250626_1613741692_n.jpg","width":150,"height":150},"standard_resolution":{"url":"https:\/\/scontent.cdninstagram.com\/hphotos-xaf1\/t51.2885-15\/s640x640\/sh0.08\/e35\/12071244_1608352556093689_1146212431_n.jpg","width":640,"height":640}},"users_in_photo":[],"caption":{"created_time":"1445650153","text":"\ud83d\udd1d #love #style @top.tags #toptags #tweegram #photooftheday #20likes #amazing #smile #follow4follow #like4like #look #instalike #igers #picoftheday #food #instadaily #instafollow #followme #girl #iphoneonly #instagood #bestoftheday #instacool #instago #all_shots #follow #webstagram #littlebrother \ud83d\ude18\ud83d\ude18","from":{"username":"marty_mtt94","profile_picture":"https:\/\/scontent.cdninstagram.com\/hphotos-xfa1\/t51.2885-19\/s150x150\/12070847_696667080486534_700989162_a.jpg","id":"2222956047","full_name":"Martina Mattisi"},"id":"1102515863305610044"},"user_has_liked":false,"id":"1102515854455628107_2222956047","user":{"username":"marty_mtt94","profile_picture":"https:\/\/scontent.cdninstagram.com\/hphotos-xfa1\/t51.2885-19\/s150x150\/12070847_696667080486534_700989162_a.jpg","id":"2222956047","full_name":"Martina Mattisi"}},{"attribution":null,"tags":["playstation","australia","england","gtafive","rockstargames","money","grandtheftauto","gta5","xboxone","gtav","gtaonline","follow4follow","ps3","unitedkingdom","gta","italy","paris","gtafiveonline","xbox","psn","gaming","ireland"],"type":"image","location":null,"comments":{"count":0,"data":[]},"filter":"Normal","created_time":"1445650152","link":"https:\/\/instagram.com\/p\/9M7FLnrHcY\/","likes":{"count":4,"data":[{"username":"tickettomilan","profile_picture":"https:\/\/igcdn-photos-h-a.akamaihd.net\/hphotos-ak-xfa1\/t51.2885-19\/11353142_596103643863495_1148586846_a.jpg","id":"2102524066","full_name":"Ticket To Milan"},{"username":"freegta5moneygames","profile_picture":"https:\/\/scontent.cdninstagram.com\/hphotos-xft1\/t51.2885-19\/10535104_1507231852822732_1424339806_a.jpg","id":"1418322693","full_name":"Free GTA Money"},{"username":"grandtheftauto3","profile_picture":"https:\/\/instagramimages-a.akamaihd.net\/profiles\/anonymousUser.jpg","id":"343791318","full_name":""},{"username":"followflock.t4","profile_picture":"https:\/\/igcdn-photos-e-a.akamaihd.net\/hphotos-ak-xfa1\/t51.2885-19\/s150x150\/12142175_893953204027524_1356559557_a.jpg","id":"2248463191","full_name":"Get Followers Here"}]},"images":{"low_resolution":{"url":"https:\/\/scontent.cdninstagram.com\/hphotos-xfa1\/t51.2885-15\/s320x320\/e35\/11355848_642804979156543_1575602277_n.jpg","width":320,"height":320},"thumbnail":{"url":"https:\/\/scontent.cdninstagram.com\/hphotos-xfa1\/t51.2885-15\/s150x150\/e35\/c55.0.529.529\/12120317_900482833372783_1201592329_n.jpg","width":150,"height":150},"standard_resolution":{"url":"https:\/\/scontent.cdninstagram.com\/hphotos-xfa1\/t51.2885-15\/s480x480\/e35\/11355848_642804979156543_1575602277_n.jpg","width":480,"height":480}},"users_in_photo":[],"caption":{"created_time":"1445650152","text":"Try the newest GTA 5 Money Online Generator. Dominate the game and opponents, build forces and make them stronger without spending a lot of time or money !. Generate your Money instant and unlimited directly from your browser.. Checkout my Bio for the link.. #gta5 #gta #gtav #grandtheftauto #xboxone #playstation #rockstargames #ps3 #xbox #gtafiveonline #money #follow4follow #gaming #psn #gtaonline #gtafive #paris #italy #australia #unitedkingdom #england #ireland","from":{"username":"gtavmoneybuz","profile_picture":"https:\/\/igcdn-photos-h-a.akamaihd.net\/hphotos-ak-xat1\/t51.2885-19\/10448892_683232471751879_1581981147_a.jpg","id":"1418157844","full_name":"FREE GTA V Money"},"id":"1102515853861876874"},"user_has_liked":false,"id":"1102515849617241880_1418157844","user":{"username":"gtavmoneybuz","profile_picture":"https:\/\/igcdn-photos-h-a.akamaihd.net\/hphotos-ak-xat1\/t51.2885-19\/10448892_683232471751879_1581981147_a.jpg","id":"1418157844","full_name":"FREE GTA V Money"}},{"attribution":null,"tags":["sasukeuchiha","followback","narutoanime","instalike","instapic","likeforfollow","follow4follow","itachi","narutoanimepictures","itachiuchiha","like4follow","narutoanimefans","like","followforfollow","uchihaclan","likeback","instagood","likeforlike","sasuke","like4like","followme"],"type":"image","location":null,"comments":{"count":0,"data":[]},"filter":"Normal","created_time":"1445650152","link":"https:\/\/instagram.com\/p\/9M7FFguvWb\/","likes":{"count":12,"data":[{"username":"warriorapparel","profile_picture":"https:\/\/scontent.cdninstagram.com\/hphotos-xaf1\/t51.2885-19\/1390026_1493128707603192_27670767_a.jpg","id":"350897864","full_name":"Warrior Apparel"},{"username":"leah_monk","profile_picture":"https:\/\/igcdn-photos-a-a.akamaihd.net\/hphotos-ak-xaf1\/t51.2885-19\/s150x150\/11849946_1632786786991496_348311573_a.jpg","id":"367341136","full_name":"\u0950 Leah Gabrielle Monk"},{"username":"kvng.papaa","profile_picture":"https:\/\/scontent.cdninstagram.com\/hphotos-xaf1\/t51.2885-19\/s150x150\/11326354_849845101751770_1276363821_a.jpg","id":"366101444","full_name":""},{"username":"hey_isabella_","profile_picture":"https:\/\/scontent.cdninstagram.com\/hphotos-xaf1\/t51.2885-19\/s150x150\/12142534_198476340489876_414507701_a.jpg","id":"350111342","full_name":"ISABELLA COLQUETTE"}]},"images":{"low_resolution":{"url":"https:\/\/scontent.cdninstagram.com\/hphotos-xaf1\/t51.2885-15\/s320x320\/e35\/12105235_107737419587371_940214066_n.jpg","width":320,"height":320},"thumbnail":{"url":"https:\/\/scontent.cdninstagram.com\/hphotos-xaf1\/t51.2885-15\/s150x150\/e35\/c0.43.344.344\/12093270_1481360852194166_399844119_n.jpg","width":150,"height":150},"standard_resolution":{"url":"https:\/\/scontent.cdninstagram.com\/hphotos-xaf1\/t51.2885-15\/s320x320\/e35\/12105235_107737419587371_940214066_n.jpg","width":320,"height":320}},"users_in_photo":[],"caption":{"created_time":"1445650152","text":"LOL \ud83d\ude02 #itachiuchiha #sasukeuchiha #itachi #sasuke #uchihaclan #narutoanime #narutoanimefans #narutoanimepictures  #instapic #like #likeforlike #like4like #likeforfollow #instalike #like4follow #followme #follow4follow #followforfollow #instagood #followback #likeback","from":{"username":"rafidamara99","profile_picture":"https:\/\/scontent.cdninstagram.com\/hphotos-xaf1\/t51.2885-19\/s150x150\/12063199_937426636328573_988809229_a.jpg","id":"2083793772","full_name":"Damara Ootsutsuki"},"id":"1102515847781086402"},"user_has_liked":false,"id":"1102515843058300315_2083793772","user":{"username":"rafidamara99","profile_picture":"https:\/\/scontent.cdninstagram.com\/hphotos-xaf1\/t51.2885-19\/s150x150\/12063199_937426636328573_988809229_a.jpg","id":"2083793772","full_name":"Damara Ootsutsuki"}},{"attribution":null,"tags":["instagram","likeme","siguemeytesigo","insta","gala","follow4follow","instasantiago","formal","f","i","l","s","f4f","sigueme","like4like","followme","l4l"],"type":"image","location":null,"comments":{"count":0,"data":[]},"filter":"Normal","created_time":"1445650151","link":"https:\/\/instagram.com\/p\/9M7FAPMuhE\/","likes":{"count":11,"data":[{"username":"k_mi.au","profile_picture":"https:\/\/scontent.cdninstagram.com\/hphotos-xfa1\/t51.2885-19\/s150x150\/12145133_532297393606176_1198447408_a.jpg","id":"290396528","full_name":"k\u00fcyen\ud83c\udf19"},{"username":"leah_monk","profile_picture":"https:\/\/igcdn-photos-a-a.akamaihd.net\/hphotos-ak-xaf1\/t51.2885-19\/s150x150\/11849946_1632786786991496_348311573_a.jpg","id":"367341136","full_name":"\u0950 Leah Gabrielle Monk"},{"username":"nawal753","profile_picture":"https:\/\/igcdn-photos-a-a.akamaihd.net\/hphotos-ak-xfa1\/t51.2885-19\/s150x150\/11910506_468873923293280_1908377341_a.jpg","id":"622095211","full_name":"Nawal \ud83c\udf8e"},{"username":"coisher","profile_picture":"https:\/\/igcdn-photos-c-a.akamaihd.net\/hphotos-ak-xpf1\/t51.2885-19\/10483537_1434644813480026_580368582_a.jpg","id":"624733300","full_name":"Taylor Coish"}]},"images":{"low_resolution":{"url":"https:\/\/scontent.cdninstagram.com\/hphotos-xfa1\/t51.2885-15\/s320x320\/e35\/12106214_1475190019457359_1307786530_n.jpg","width":320,"height":320},"thumbnail":{"url":"https:\/\/scontent.cdninstagram.com\/hphotos-xfa1\/t51.2885-15\/s150x150\/e35\/12106214_1475190019457359_1307786530_n.jpg","width":150,"height":150},"standard_resolution":{"url":"https:\/\/scontent.cdninstagram.com\/hphotos-xfa1\/t51.2885-15\/s640x640\/sh0.08\/e35\/12106214_1475190019457359_1307786530_n.jpg","width":640,"height":640}},"users_in_photo":[],"caption":{"created_time":"1445650151","text":"En camino a la gala \ud83d\ude0e #insta #instasantiago #i #likeme #formal #gala #f #followme #f4f #follow4follow #l #l4l #likeme #like4like #instagram #siguemeytesigo #sigueme #s","from":{"username":"zebha_vm","profile_picture":"https:\/\/igcdn-photos-b-a.akamaihd.net\/hphotos-ak-xpa1\/t51.2885-19\/s150x150\/10848112_1611249649145961_1621944792_a.jpg","id":"2159343257","full_name":"seba \ud83d\ude24"},"id":"1102515840625076813"},"user_has_liked":false,"id":"1102515837395462212_2159343257","user":{"username":"zebha_vm","profile_picture":"https:\/\/igcdn-photos-b-a.akamaihd.net\/hphotos-ak-xpa1\/t51.2885-19\/s150x150\/10848112_1611249649145961_1621944792_a.jpg","id":"2159343257","full_name":"seba \ud83d\ude24"}},{"attribution":null,"tags":["fashion","love","followhim","likeforfollow","selfie","makeup","instalove","selfies","throwback","igers","follow4follow","girlfriend","follow","followtrain","swag","like4follow","followforfollow","followall","fashionista","followme","instacollage","bestoftheday","fitness","f4f","model","bored","beach","picoftheday"],"type":"image","location":null,"comments":{"count":0,"data":[]},"filter":"Normal","created_time":"1445650151","link":"https:\/\/instagram.com\/p\/9M7E_rBJY0\/","likes":{"count":10,"data":[{"username":"chujing0","profile_picture":"https:\/\/scontent.cdninstagram.com\/hphotos-xfa1\/t51.2885-19\/s150x150\/11809922_1044504158894773_1127044513_a.jpg","id":"19079774","full_name":"Wun\u264c\ufe0f\ud83d\udc95"},{"username":"kvng.papaa","profile_picture":"https:\/\/scontent.cdninstagram.com\/hphotos-xaf1\/t51.2885-19\/s150x150\/11326354_849845101751770_1276363821_a.jpg","id":"366101444","full_name":""},{"username":"mimitoamin","profile_picture":"https:\/\/igcdn-photos-a-a.akamaihd.net\/hphotos-ak-xaf1\/t51.2885-19\/s150x150\/12142201_1034432653275608_1530996569_a.jpg","id":"281094749","full_name":"Mimito Amin"},{"username":"hey_isabella_","profile_picture":"https:\/\/scontent.cdninstagram.com\/hphotos-xaf1\/t51.2885-19\/s150x150\/12142534_198476340489876_414507701_a.jpg","id":"350111342","full_name":"ISABELLA COLQUETTE"}]},"images":{"low_resolution":{"url":"https:\/\/scontent.cdninstagram.com\/hphotos-xaf1\/t51.2885-15\/s320x320\/e35\/11349435_186739398327778_539118136_n.jpg","width":320,"height":320},"thumbnail":{"url":"https:\/\/scontent.cdninstagram.com\/hphotos-xaf1\/t51.2885-15\/s150x150\/e35\/11349435_186739398327778_539118136_n.jpg","width":150,"height":150},"standard_resolution":{"url":"https:\/\/scontent.cdninstagram.com\/hphotos-xaf1\/t51.2885-15\/e35\/11349435_186739398327778_539118136_n.jpg","width":640,"height":640}},"users_in_photo":[],"caption":{"created_time":"1445650151","text":"\ud83d\udc8e Do you want more followers? \ud83d\udc8e\ud83d\udea8 Just go to the site in my bio \ud83d\udea8\ud83d\udc8e Only works for a limited time. \ud83d\udc8e \ud83d\udea8\ud83d\udea8\n#followhim #followall #followtrain #instacollage #selfies #followme #beach #instalove #girlfriend #throwback #makeup #fitness #selfie #bored #picoftheday #likeforfollow #followforfollow #follow4follow #fashion #f4f #like4follow #model #love #bestoftheday #fashionista #igers #swag #follow","from":{"username":"followflock.s4","profile_picture":"https:\/\/scontent.cdninstagram.com\/hphotos-xaf1\/t51.2885-19\/s150x150\/12139570_1652891521662220_1523054827_a.jpg","id":"2248445292","full_name":"Get Followers Here"},"id":"1102515838323561915"},"user_has_liked":false,"id":"1102515836788446772_2248445292","user":{"username":"followflock.s4","profile_picture":"https:\/\/scontent.cdninstagram.com\/hphotos-xaf1\/t51.2885-19\/s150x150\/12139570_1652891521662220_1523054827_a.jpg","id":"2248445292","full_name":"Get Followers Here"}},{"attribution":null,"tags":["l4l","eyes","colorful","nofilter","life","hair","tagsforlikesapp","instago","follow4follow","my","reinadelpop","cool","funny","style","webstagram","look","instafollow","iphoneonly","20likes","lol","tagsforlikes","instacool","likeforlike","pretty","martasanchez","bored","tweegram","nice"],"type":"image","location":null,"comments":{"count":0,"data":[]},"filter":"Clarendon","created_time":"1445650150","link":"https:\/\/instagram.com\/p\/9M7E6BK3is\/","likes":{"count":16,"data":[{"username":"milica_stankic7","profile_picture":"https:\/\/igcdn-photos-a-a.akamaihd.net\/hphotos-ak-xfa1\/t51.2885-19\/s150x150\/12106055_1102150429795872_618997701_a.jpg","id":"1532375625","full_name":"Milica Stanki\u0107"},{"username":"micaaaortiz","profile_picture":"https:\/\/scontent.cdninstagram.com\/hphotos-xaf1\/t51.2885-19\/s150x150\/12132873_749126385216057_466419798_a.jpg","id":"1785732115","full_name":"\ud83d\udc51QueenMicaela\ud83d\udc51"},{"username":"asakonina","profile_picture":"https:\/\/scontent.cdninstagram.com\/hphotos-xaf1\/t51.2885-19\/11377939_1612571512331384_68848778_a.jpg","id":"1712786876","full_name":"ASAKO.N.S."},{"username":"ritinhalmeida96","profile_picture":"https:\/\/scontent.cdninstagram.com\/hphotos-xaf1\/t51.2885-19\/11371012_1625986147656638_894488208_a.jpg","id":"1599990044","full_name":"Rita Almeida"}]},"images":{"low_resolution":{"url":"https:\/\/scontent.cdninstagram.com\/hphotos-xaf1\/t51.2885-15\/s320x320\/e35\/12106138_607901812681244_574982114_n.jpg","width":320,"height":320},"thumbnail":{"url":"https:\/\/scontent.cdninstagram.com\/hphotos-xfa1\/t51.2885-15\/s150x150\/e35\/c0.49.726.726\/12135296_1667860496765051_1074723575_n.jpg","width":150,"height":150},"standard_resolution":{"url":"https:\/\/scontent.cdninstagram.com\/hphotos-xaf1\/t51.2885-15\/s640x640\/sh0.08\/e35\/12106138_607901812681244_574982114_n.jpg","width":640,"height":640}},"users_in_photo":[{"position":{"y":0.4515625,"x":0.3244318},"user":{"username":"martisimasanchez","profile_picture":"https:\/\/scontent.cdninstagram.com\/hphotos-xfa1\/t51.2885-19\/s150x150\/11311172_145806052422875_562342306_a.jpg","id":"421915373","full_name":"Marta S\u00e1nchez"}},{"position":{"y":0.284375,"x":0.2056129},"user":{"username":"martasanchez_reinadelpop","profile_picture":"https:\/\/igcdn-photos-e-a.akamaihd.net\/hphotos-ak-xfa1\/t51.2885-19\/s150x150\/11374466_1149928455036348_1921513120_a.jpg","id":"2180412781","full_name":"Marta Sanchez Reina Del Pop"}}],"caption":{"created_time":"1445650150","text":"Buenas noches\ud83d\udc96\u2b50\ufe0f @martisimasanchez #martasanchez #reinadelpop #nofilter #TagsForLikesApp #TagsForLikes.com #webstagram #follow4follow #iphoneonly #instago #pretty #l4l #my #style #instacool #life #hair #instafollow #likeforlike #eyes #20likes #funny #colorful #bored #look #lol #tweegram #nice #cool","from":{"username":"martasanchez_reinadelpop","profile_picture":"https:\/\/igcdn-photos-e-a.akamaihd.net\/hphotos-ak-xfa1\/t51.2885-19\/s150x150\/11374466_1149928455036348_1921513120_a.jpg","id":"2180412781","full_name":"Marta Sanchez Reina Del Pop"},"id":"1102515834509293813"},"user_has_liked":false,"id":"1102515830717642924_2180412781","user":{"username":"martasanchez_reinadelpop","profile_picture":"https:\/\/igcdn-photos-e-a.akamaihd.net\/hphotos-ak-xfa1\/t51.2885-19\/s150x150\/11374466_1149928455036348_1921513120_a.jpg","id":"2180412781","full_name":"Marta Sanchez Reina Del Pop"}},{"attribution":null,"tags":["mike","hkboy","family","luke","yo","hk","hkig","hkiger","follow4follow","ashton","iger","teammate","disconnected","followforfollow","hongkong","hkgirl","instagood","cpy","calum","likeforlike","5sos","5secondsofsummer","like4like","instamood"],"type":"image","location":null,"comments":{"count":3,"data":[{"created_time":"1445650158","text":"#hongkong #hkig #hkboy #hk #hkgirl #instamood #instagood #teammate #cpy #family #likeforlike #like4like #followforfollow #follow4follow","from":{"username":"xpx8ny.w_","profile_picture":"https:\/\/scontent.cdninstagram.com\/hphotos-xaf1\/t51.2885-19\/s150x150\/12070846_1057585820939792_916272442_a.jpg","id":"1419222401","full_name":"Ched Wan\ud83d\ude46\ud83c\udfff"},"id":"1102515896265836981"},{"created_time":"1445650192","text":"#yo #hkiger #iger #5secondsofsummer #luke #calum #mike #ashton","from":{"username":"xpx8ny.w_","profile_picture":"https:\/\/scontent.cdninstagram.com\/hphotos-xaf1\/t51.2885-19\/s150x150\/12070846_1057585820939792_916272442_a.jpg","id":"1419222401","full_name":"Ched Wan\ud83d\ude46\ud83c\udfff"},"id":"1102516185664424391"},{"created_time":"1445650518","text":"#MyManAha","from":{"username":"lukehegxx","profile_picture":"https:\/\/scontent.cdninstagram.com\/hphotos-xaf1\/t51.2885-19\/s150x150\/12071010_1481685825467505_1294604873_a.jpg","id":"619114251","full_name":"Hegel G. C.\ud83d\udc27"},"id":"1102518920224803465"}]},"filter":"Normal","created_time":"1445650149","link":"https:\/\/instagram.com\/p\/9M7Ex8pYqp\/","likes":{"count":8,"data":[{"username":"leah_monk","profile_picture":"https:\/\/igcdn-photos-a-a.akamaihd.net\/hphotos-ak-xaf1\/t51.2885-19\/s150x150\/11849946_1632786786991496_348311573_a.jpg","id":"367341136","full_name":"\u0950 Leah Gabrielle Monk"},{"username":"lukehegxx","profile_picture":"https:\/\/scontent.cdninstagram.com\/hphotos-xaf1\/t51.2885-19\/s150x150\/12071010_1481685825467505_1294604873_a.jpg","id":"619114251","full_name":"Hegel G. C.\ud83d\udc27"},{"username":"xxmdc__","profile_picture":"https:\/\/scontent.cdninstagram.com\/hphotos-xfa1\/t51.2885-19\/s150x150\/12139688_1632445770361962_279525982_a.jpg","id":"252983191","full_name":"Mandyyyyyyy\ud83d\ude18"},{"username":"call_me_circle","profile_picture":"https:\/\/igcdn-photos-a-a.akamaihd.net\/hphotos-ak-xaf1\/t51.2885-19\/s150x150\/11906110_687455761387568_249878724_a.jpg","id":"1222534975","full_name":"\u5713\u5f62\u4e00\u500b"}]},"images":{"low_resolution":{"url":"https:\/\/scontent.cdninstagram.com\/hphotos-xap1\/t51.2885-15\/s320x320\/e35\/10890765_1668904103350184_1213190210_n.jpg","width":320,"height":320},"thumbnail":{"url":"https:\/\/scontent.cdninstagram.com\/hphotos-xaf1\/t51.2885-15\/s150x150\/e35\/c0.100.800.800\/12142560_559362850898048_1117519038_n.jpg","width":150,"height":150},"standard_resolution":{"url":"https:\/\/scontent.cdninstagram.com\/hphotos-xap1\/t51.2885-15\/s640x640\/sh0.08\/e35\/10890765_1668904103350184_1213190210_n.jpg","width":640,"height":640}},"users_in_photo":[],"caption":{"created_time":"1445650149","text":"-\n#Disconnected \nI like the summer rain\nI like the sounds you make\nWe put the world away\nWe get so disconnected\nYou are my getaway\nYou are my favorite place\nWe put the world away\nYeah we're so disconnected\n#5sos","from":{"username":"xpx8ny.w_","profile_picture":"https:\/\/scontent.cdninstagram.com\/hphotos-xaf1\/t51.2885-19\/s150x150\/12070846_1057585820939792_916272442_a.jpg","id":"1419222401","full_name":"Ched Wan\ud83d\ude46\ud83c\udfff"},"id":"1102515831279290799"},"user_has_liked":false,"id":"1102515822051822249_1419222401","user":{"username":"xpx8ny.w_","profile_picture":"https:\/\/scontent.cdninstagram.com\/hphotos-xaf1\/t51.2885-19\/s150x150\/12070846_1057585820939792_916272442_a.jpg","id":"1419222401","full_name":"Ched Wan\ud83d\ude46\ud83c\udfff"}},{"attribution":null,"tags":["booty","picoftheday","colorful","look","food","instalike","curves","instago","igers","follow4follow","follow","instadaily","thick","assets","style","like4like","kuelios","girl","instafollow","iphoneonly","girls","thickest","all_shots","instagood","curvy","instacool","bestoftheday","webstagram","followme"],"type":"image","location":null,"comments":{"count":0,"data":[]},"filter":"Normal","created_time":"1445650149","link":"https:\/\/instagram.com\/p\/9M7EvlwNNi\/","likes":{"count":26,"data":[{"username":"www_itsomee_com","profile_picture":"https:\/\/scontent.cdninstagram.com\/hphotos-xfa1\/t51.2885-19\/s150x150\/12145244_1471021856540074_121154388_a.jpg","id":"1990707288","full_name":"ITSOMEE"},{"username":"whyshyngmail","profile_picture":"https:\/\/scontent.cdninstagram.com\/hphotos-xaf1\/t51.2885-19\/s150x150\/11419243_797647260353232_550600958_a.jpg","id":"1915433748","full_name":"\u0627\u0645 \u0641\u0627\u0631\u0633"},{"username":"luis181354","profile_picture":"https:\/\/igcdn-photos-b-a.akamaihd.net\/hphotos-ak-xaf1\/t51.2885-19\/s150x150\/11821324_668627479941209_1919599755_a.jpg","id":"2029113362","full_name":"luis miguel escobar caballero"},{"username":"oswaldoduranosorio","profile_picture":"https:\/\/scontent.cdninstagram.com\/hphotos-xaf1\/t51.2885-19\/s150x150\/11352354_959919127397985_1593562532_a.jpg","id":"2045683068","full_name":"oswaldo duran osorio"}]},"images":{"low_resolution":{"url":"https:\/\/scontent.cdninstagram.com\/hphotos-xaf1\/t51.2885-15\/s320x320\/e35\/12139686_888373964574161_341223972_n.jpg","width":320,"height":320},"thumbnail":{"url":"https:\/\/scontent.cdninstagram.com\/hphotos-xaf1\/t51.2885-15\/s150x150\/e35\/12139686_888373964574161_341223972_n.jpg","width":150,"height":150},"standard_resolution":{"url":"https:\/\/scontent.cdninstagram.com\/hphotos-xaf1\/t51.2885-15\/e35\/12139686_888373964574161_341223972_n.jpg","width":640,"height":640}},"users_in_photo":[{"position":{"y":0.8046875,"x":0.328125},"user":{"username":"iambeataylor","profile_picture":"https:\/\/scontent.cdninstagram.com\/hphotos-xfa1\/t51.2885-19\/s150x150\/11850059_439602136247045_1231844977_a.jpg","id":"31746081","full_name":"IAmBeaTaylor"}},{"position":{"y":0.2203125,"x":0.78125},"user":{"username":"bootyjournalist","profile_picture":"https:\/\/igcdn-photos-a-a.akamaihd.net\/hphotos-ak-xaf1\/t51.2885-19\/11428707_1693462927542464_1537302410_a.jpg","id":"1809720178","full_name":""}}],"caption":{"created_time":"1445650149","text":"#follow4follow #like4like #look #instalike #igers #picoftheday #food #instadaily #instafollow #followme #girl #iphoneonly #instagood #bestoftheday #instacool #instago #all_shots #follow #webstagram #colorful #style #kuelios #curves #booty #girls #thick #thickest #curvy #assets\n tag us in your pics for a shout","from":{"username":"officialkuelios","profile_picture":"https:\/\/scontent.cdninstagram.com\/hphotos-xaf1\/t51.2885-19\/s150x150\/12093636_152299841784132_956808143_a.jpg","id":"1989509147","full_name":"k u e l i o s \u00ae"},"id":"1102515821709676847"},"user_has_liked":false,"id":"1102515819520250722_1989509147","user":{"username":"officialkuelios","profile_picture":"https:\/\/scontent.cdninstagram.com\/hphotos-xaf1\/t51.2885-19\/s150x150\/12093636_152299841784132_956808143_a.jpg","id":"1989509147","full_name":"k u e l i o s \u00ae"}},{"attribution":null,"tags":["love","picoftheday","colorful","food","instalike","swag","instago","igers","follow4follow","follow","instadaily","girl","style","webstagram","tflers","look","instafollow","iphoneonly","20likes","all_shots","instagood","tagsforlikes","amazing","instacool","bestoftheday","smile","like4like","tweegram","followme","photooftheday"],"type":"image","location":null,"comments":{"count":0,"data":[]},"filter":"Normal","created_time":"1445650148","link":"https:\/\/instagram.com\/p\/9M7Er_I6rp\/","likes":{"count":15,"data":[{"username":"leah_monk","profile_picture":"https:\/\/igcdn-photos-a-a.akamaihd.net\/hphotos-ak-xaf1\/t51.2885-19\/s150x150\/11849946_1632786786991496_348311573_a.jpg","id":"367341136","full_name":"\u0950 Leah Gabrielle Monk"},{"username":"milica_stankic7","profile_picture":"https:\/\/igcdn-photos-a-a.akamaihd.net\/hphotos-ak-xfa1\/t51.2885-19\/s150x150\/12106055_1102150429795872_618997701_a.jpg","id":"1532375625","full_name":"Milica Stanki\u0107"},{"username":"cla3m_f0ll0werzs","profile_picture":"https:\/\/igcdn-photos-e-a.akamaihd.net\/hphotos-ak-xaf1\/t51.2885-19\/s150x150\/11410515_408923609314692_1181410176_a.jpg","id":"617353315","full_name":""},{"username":"ay00_1ooo_f0llws","profile_picture":"https:\/\/igcdn-photos-g-a.akamaihd.net\/hphotos-ak-xaf1\/t51.2885-19\/s150x150\/11849907_1620583554885238_937560964_a.jpg","id":"1821196392","full_name":""}]},"images":{"low_resolution":{"url":"https:\/\/scontent.cdninstagram.com\/hphotos-xfp1\/t51.2885-15\/s320x320\/e35\/1741011_889787124469554_211622131_n.jpg","width":320,"height":320},"thumbnail":{"url":"https:\/\/scontent.cdninstagram.com\/hphotos-xfp1\/t51.2885-15\/s150x150\/e35\/1741011_889787124469554_211622131_n.jpg","width":150,"height":150},"standard_resolution":{"url":"https:\/\/scontent.cdninstagram.com\/hphotos-xfp1\/t51.2885-15\/s640x640\/sh0.08\/e35\/1741011_889787124469554_211622131_n.jpg","width":640,"height":640}},"users_in_photo":[],"caption":{"created_time":"1445650148","text":"TONGUE! \ud83d\ude0d\ud83d\udc4a\ud83c\udffe\ud83d\udc45\n#love #TagsForLikes @TagsForLikes #TFLers #tweegram #photooftheday #20likes #amazing #smile #follow4follow #like4like #look #instalike #igers #picoftheday #food #instadaily #instafollow #followme #girl #iphoneonly #instagood #bestoftheday #instacool #instago #all_shots #follow #webstagram #colorful #style #swag","from":{"username":"seredanifulci_","profile_picture":"https:\/\/scontent.cdninstagram.com\/hphotos-xaf1\/t51.2885-19\/s150x150\/11821707_1615376518712946_1419073590_a.jpg","id":"259722281","full_name":"Serena Fulciniti"},"id":"1102515822689233783"},"user_has_liked":false,"id":"1102515815651191529_259722281","user":{"username":"seredanifulci_","profile_picture":"https:\/\/scontent.cdninstagram.com\/hphotos-xaf1\/t51.2885-19\/s150x150\/11821707_1615376518712946_1419073590_a.jpg","id":"259722281","full_name":"Serena Fulciniti"}}]}